mogic_object_utils
